{
  "package_url": "\"C:\\Users\\ajers\\AppData\\Local\\Programs\\MiKTeX\\miktex\\bin\\x64\\miktex.exe\"",
  "timeout": 10000,
  "enableCache": true,
  "invertColorsInDarkMode": true,
  "cache": [
    [
      "68caebf75fd353feedb658a90e084b34",
      [
        "0EVAU/Filosofía/Platón.md"
      ]
    ]
  ],
  "packageCache": [
    {
      "26/main.aux": 1,
      "33/cmr10.vf": 1,
      "26/pd1enc.dfu": 1,
      "26/hyperref.cfg": 1,
      "26/rerunfilecheck.cfg": 1,
      "26/gettitlestring.cfg": 1,
      "26/main.out": 1,
      "33/cmr17.vf": 1,
      "33/cmr12.vf": 1,
      "33/cmbx12.vf": 1,
      "33/cmtt10.vf": 1,
      "33/cmmi10.vf": 1,
      "33/cmr7.vf": 1
    },
    {
      "10/swiftlatexpdftex.fmt": "/tex/swiftlatexpdftex.fmt",
      "26/article.cls": "/tex/article.cls",
      "26/size10.clo": "/tex/size10.clo",
      "26/amssymb.sty": "/tex/amssymb.sty",
      "26/amsfonts.sty": "/tex/amsfonts.sty",
      "26/latexsym.sty": "/tex/latexsym.sty",
      "26/amsmath.sty": "/tex/amsmath.sty",
      "26/amstext.sty": "/tex/amstext.sty",
      "26/amsgen.sty": "/tex/amsgen.sty",
      "26/amsbsy.sty": "/tex/amsbsy.sty",
      "26/amsopn.sty": "/tex/amsopn.sty",
      "26/l3backend-pdfmode.def": "/tex/l3backend-pdfmode.def",
      "11/pdftex.map": "/tex/pdftex.map",
      "32/cmr10.pfb": "/tex/cmr10.pfb",
      "26/graphicx.sty": "/tex/graphicx.sty",
      "26/keyval.sty": "/tex/keyval.sty",
      "26/graphics.sty": "/tex/graphics.sty",
      "26/trig.sty": "/tex/trig.sty",
      "26/graphics.cfg": "/tex/graphics.cfg",
      "26/pdftex.def": "/tex/pdftex.def",
      "26/booktabs.sty": "/tex/booktabs.sty",
      "26/hyperref.sty": "/tex/hyperref.sty",
      "26/ltxcmds.sty": "/tex/ltxcmds.sty",
      "26/iftex.sty": "/tex/iftex.sty",
      "26/pdftexcmds.sty": "/tex/pdftexcmds.sty",
      "26/infwarerr.sty": "/tex/infwarerr.sty",
      "26/kvsetkeys.sty": "/tex/kvsetkeys.sty",
      "26/kvdefinekeys.sty": "/tex/kvdefinekeys.sty",
      "26/pdfescape.sty": "/tex/pdfescape.sty",
      "26/hycolor.sty": "/tex/hycolor.sty",
      "26/letltxmacro.sty": "/tex/letltxmacro.sty",
      "26/auxhook.sty": "/tex/auxhook.sty",
      "26/kvoptions.sty": "/tex/kvoptions.sty",
      "26/pd1enc.def": "/tex/pd1enc.def",
      "26/intcalc.sty": "/tex/intcalc.sty",
      "26/etexcmds.sty": "/tex/etexcmds.sty",
      "26/url.sty": "/tex/url.sty",
      "26/bitset.sty": "/tex/bitset.sty",
      "26/bigintcalc.sty": "/tex/bigintcalc.sty",
      "26/atbegshi.sty": "/tex/atbegshi.sty",
      "26/hpdftex.def": "/tex/hpdftex.def",
      "26/atveryend.sty": "/tex/atveryend.sty",
      "26/rerunfilecheck.sty": "/tex/rerunfilecheck.sty",
      "26/uniquecounter.sty": "/tex/uniquecounter.sty",
      "26/xcolor.sty": "/tex/xcolor.sty",
      "26/color.cfg": "/tex/color.cfg",
      "26/supp-pdf.mkii": "/tex/supp-pdf.mkii",
      "26/nameref.sty": "/tex/nameref.sty",
      "26/refcount.sty": "/tex/refcount.sty",
      "26/gettitlestring.sty": "/tex/gettitlestring.sty",
      "3/cmr17": "/tex/cmr17.tfm",
      "3/cmr12": "/tex/cmr12.tfm",
      "3/cmr8": "/tex/cmr8.tfm",
      "3/cmr6": "/tex/cmr6.tfm",
      "3/cmmi12": "/tex/cmmi12.tfm",
      "3/cmmi8": "/tex/cmmi8.tfm",
      "3/cmmi6": "/tex/cmmi6.tfm",
      "3/cmsy10": "/tex/cmsy10.tfm",
      "3/cmsy8": "/tex/cmsy8.tfm",
      "3/cmsy6": "/tex/cmsy6.tfm",
      "3/cmex10": "/tex/cmex10.tfm",
      "3/cmex8": "/tex/cmex8.tfm",
      "3/cmex7": "/tex/cmex7.tfm",
      "26/umsa.fd": "/tex/umsa.fd",
      "3/msam10": "/tex/msam10.tfm",
      "3/msam7": "/tex/msam7.tfm",
      "26/umsb.fd": "/tex/umsb.fd",
      "3/msbm10": "/tex/msbm10.tfm",
      "3/msbm7": "/tex/msbm7.tfm",
      "3/cmbx12": "/tex/cmbx12.tfm",
      "3/cmtt10": "/tex/cmtt10.tfm",
      "3/msam5": "/tex/msam5.tfm",
      "3/msbm5": "/tex/msbm5.tfm",
      "26/example-image.pdf": "/tex/example-image.pdf",
      "32/lmss17.pfb": "/tex/lmss17.pfb",
      "32/cmbx12.pfb": "/tex/cmbx12.pfb",
      "32/cmmi10.pfb": "/tex/cmmi10.pfb",
      "32/cmr12.pfb": "/tex/cmr12.pfb",
      "32/cmr17.pfb": "/tex/cmr17.pfb",
      "32/cmr7.pfb": "/tex/cmr7.pfb",
      "32/cmtt10.pfb": "/tex/cmtt10.pfb"
    },
    {},
    {}
  ],
  "onlyRenderInReadingMode": false
}