{
  "obsidian-excalidraw-plugin:fullscreen": [
    {
      "modifiers": [
        "Alt"
      ],
      "key": "F"
    }
  ],
  "editor:insert-wikilink": [
    {
      "modifiers": [
        "Alt"
      ],
      "key": "L"
    }
  ],
  "templater-obsidian:C:\\MyPrograms\\Obsidian\\Life\\Snippets": [
    {
      "modifiers": [
        "Alt"
      ],
      "key": "B"
    }
  ],
  "templater-obsidian:C:\\MyPrograms\\Obsidian\\Life\\Snippets\\blue.txt": [
    {
      "modifiers": [
        "Alt"
      ],
      "key": "C"
    }
  ],
  "templater-obsidian:C:\\MyPrograms\\Obsidian\\Life\\Snippets\\formula.txt": [
    {
      "modifiers": [
        "Alt"
      ],
      "key": "B"
    }
  ],
  "templater-obsidian:Snippets/blue.txt": [
    {
      "modifiers": [
        "Alt"
      ],
      "key": "C"
    }
  ],
  "templater-obsidian:Snippets/formula.txt": [
    {
      "modifiers": [
        "Alt"
      ],
      "key": "4"
    }
  ],
  "templater-obsidian:Snippets/html_Bold.txt": [
    {
      "modifiers": [
        "Alt"
      ],
      "key": "B"
    }
  ],
  "templater-obsidian:Snippets/html_Highlight.txt": [
    {
      "modifiers": [
        "Alt"
      ],
      "key": "H"
    }
  ],
  "obsidian-hider:toggle-hider-status": [
    {
      "modifiers": [
        "Alt",
        "Mod"
      ],
      "key": "H"
    }
  ],
  "templater-obsidian:Snippets/html_Important.txt": [
    {
      "modifiers": [
        "Alt"
      ],
      "key": "N"
    }
  ],
  "templater-obsidian:create-new-note-from-template": [],
  "templater-obsidian:Snippets/tab.txt": [
    {
      "modifiers": [
        "Mod"
      ],
      "key": "Tab"
    }
  ],
  "workspace:next-tab": [
    {
      "modifiers": [
        "Ctrl"
      ],
      "key": "PageDown"
    },
    {
      "modifiers": [
        "Mod"
      ],
      "key": "ArrowRight"
    }
  ],
  "templater-obsidian:Snippets/html_Underline.txt": [
    {
      "modifiers": [
        "Alt"
      ],
      "key": "U"
    }
  ],
  "editor:toggle-highlight": [
    {
      "modifiers": [
        "Mod"
      ],
      "key": "="
    }
  ],
  "outline:open": [
    {
      "modifiers": [
        "Mod"
      ],
      "key": "\\"
    }
  ],
  "templater-obsidian:Snippets/line.txt": [
    {
      "modifiers": [
        "Alt"
      ],
      "key": "-"
    }
  ],
  "templater-obsidian:Snippets/waypoint.txt": [
    {
      "modifiers": [
        "Alt"
      ],
      "key": "W"
    }
  ],
  "templater-obsidian:Snippets/landmark.txt": [
    {
      "modifiers": [
        "Alt",
        "Mod"
      ],
      "key": "W"
    }
  ]
}